RoleMiner/functions.py
RoleMiner-0.1.1.dist-info/LICENSE
RoleMiner-0.1.1.dist-info/METADATA
RoleMiner-0.1.1.dist-info/WHEEL
RoleMiner-0.1.1.dist-info/top_level.txt
RoleMiner-0.1.1.dist-info/RECORD
